Workbook

Sheet Start Here
B1: Business Acquisition Analyzer (Free Demo)
B2: FREE DEMO by LaneLedger Co. · Microsoft Excel and Google Sheets
B4: Find what a small business really earns, what it is worth, and the most its cash flow can support.
B6: What this free demo includes
B7: • SDE Normalization: 3 years of financials with owner add-backs and deductions
B8: • Valuation: SDE multiple value range, asking and offer multiples
B9: • Maximum supportable price at your target DSCR (SBA-style loan)
B11: The full version adds
B12: • Financing: sources & uses, loan and seller note payments, DSCR and instant lender checks
B13: • Offer Scenarios: compare 3 deal structures side by side
B14: • 10-Year Projection: owner cash flow, debt paydown, equity at exit and IRR
B15: • One-page Deal Summary with pass / fail verdict, and a 31-item Due Diligence checklist
... B22: This demo is free to use in your own business. Please don't resell it.

Sheet Deal Inputs
A1: Deal Inputs
A2: The deal you are evaluating. Every other tab reads from here.
A4: The business
A5: Business name | B5: Example: Coastal HVAC Services
A6: Industry | B6: HVAC / home services
A7: Location | B7: Tampa, FL
A9: Price
A10: Asking price | B10: 1850000
A11: Your offer price (base case) | B11: 1750000 | D11: Used for Financing, Projection and Deal Summary.
A12: Working capital needed at closing | B12: 75000 | D12: Cash the business needs on day one (inventory, receivables float).
A13: Closing costs (legal, QoE, appraisal, etc.) | B13: 40000
A14: Lender & guarantee fees (% of loan, estimate) | B14: 0.03 | D14: Your estimate. Ask your lender for the actual fee schedule.
A16: Financing
A17: Buyer cash injection (% of price + WC + closing) | B17: 0.1
A18: Minimum cash injection the lender requires | B18: 0.1 | D18: Often around 10% for SBA 7(a) acquisitions. Confirm with your lender.
A19: Seller note (% of price) | B19: 0.1
A20: Seller note interest rate | B20: 0.06
A21: Seller note repayment term (years) | B21: 5
A22: Seller note standby (years with no payments) | B22: 2 | D22: Payments start after the standby period. Some lenders require full standby.
A23: Bank / SBA loan interest rate | B23: 0.105 | D23: Your estimate. Rates change.
A24: Bank / SBA loan term (years) | B24: 10
A25: Target DSCR | B25: 1.25 | D25: Many lenders look for 1.25x or higher. Some want more.
A27: Operating assumptions
A28: Your salary as the new owner (market rate) | B28: 110000 | D28: What you would pay a manager to run it. Subtracted from SDE before debt service.
A29: Annual capex / equipment reserve | B29: 30000
A30: Revenue growth per year (projection) | B30: 0.03
A31: SDE margin change per year (projection) | B31: 0 | D31: e.g. 0.5% if you expect efficiency gains, -0.5% if margins will slip.
A32: Exit multiple of SDE in year 10 | B32: 2.75
A33: Owner salary increase per year | B33: 0.02

Sheet SDE Normalization
A1: SDE Normalization
A2: Turn reported profit into what the business really earns for an owner. Enter the last 3 years.
B4: Year 1 (oldest) | C4: Year 2 | D4: Year 3 (latest)
A5: Fiscal year | B5: 2023 | C5: 2024 | D5: 2025
A6: Revenue | B6: 1520000 | C6: 1640000 | D6: 1780000
A7: Cost of goods sold | B7: 640000 | C7: 680000 | D7: 735000
A8: Gross profit | B8: =B6-B7 -> 880000 | C8: =C6-C7 -> 960000 | D8: =D6-D7 -> 1045000
A9: Gross margin | B9: =IF(B6=0,0,B8/B6) -> 0.57894737 | C9: =IF(C6=0,0,C8/C6) -> 0.58536585 | D9: =IF(D6=0,0,D8/D6) -> 0.58707865
A10: Operating expenses (all, incl. owner pay) | B10: 585000 | C10: 625000 | D10: 671000
A11: Net income before tax (reported) | B11: =B8-B10 -> 295000 | C11: =C8-C10 -> 335000 | D11: =D8-D10 -> 374000
A13: Add-backs (owner & non-recurring items)
A14: Owner's salary / wages | B14: 88000 | C14: 92000 | D14: 96000 | F14: All pay to the selling owner(s).
A15: Owner payroll taxes & benefits | B15: 9000 | C15: 9500 | D15: 10000
A16: Owner health / life insurance | B16: 12000 | C16: 12500 | D16: 13000
A17: Interest expense | B17: 11000 | C17: 9500 | D17: 8000 | F17: Existing debt is usually paid off at closing.
A18: Depreciation & amortization | B18: 24000 | C18: 22000 | D18: 26000 | F18: Non-cash. Your capex reserve covers real replacement spending.
A19: One-time / non-recurring expenses | B19: 0 | C19: 18000 | D19: 0 | F19: e.g. a lawsuit, a one-off rebrand. Must be documented.
A20: Personal expenses run through the business | B20: 7000 | C20: 7500 | D20: 8000 | F20: Personal vehicle, phone, travel. Be skeptical and ask for proof.
A21: Other add-back (describe in notes) | B21: 0 | C21: 0 | D21: 0
A22: Other add-back (describe in notes) | B22: 0 | C22: 0 | D22: 0
A24: Deductions (costs the reported numbers hide)
A25: Rent adjustment to market (if owner owns the building) | B25: 0 | C25: 0 | D25: 0 | F25: If the seller pays below-market rent to themself, enter the extra rent you will pay.
A26: Other deduction (describe in notes) | B26: 0 | C26: 0 | D26: 0
A28: SDE (Seller's Discretionary Earnings) | B28: =B11+SUM(B14:B22)-SUM(B25:B26) -> 446000 | C28: =C11+SUM(C14:C22)-SUM(C25:C26) -> 506000 | D28: =D11+SUM(D14:D22)-SUM(D25:D26) -> 535000
A29: SDE margin | B29: =IF(B6=0,0,B28/B6) -> 0.29342105 | C29: =IF(C6=0,0,C28/C6) -> 0.30853659 | D29: =IF(D6=0,0,D28/D6) -> 0.3005618
A30: EBITDA (SDE minus your market salary) | B30: =B28-'Deal Inputs'!$B$28 -> 336000 | C30: =C28-'Deal Inputs'!$B$28 -> 396000 | D30: =D28-'Deal Inputs'!$B$28 -> 425000
A32: SDE used for valuation and financing
A33: Weighted average (latest year counts most: 1-2-3) | B33: =(B28*1+C28*2+D28*3)/6 -> 510500 | F33: Lenders and brokers often weight recent years more. A falling trend is a warning sign.
A34: Simple 3-year average | B34: =AVERAGE(B28:D28) -> 495666.67
A35: Latest year | B35: =D28 -> 535000
A36: Choose the basis | B36: Weighted average | F36: Pick the basis you are comfortable defending to a lender.
A37: SELECTED SDE | B37: =CHOOSE(MATCH(B36,{"Weighted average","Simple 3-year average","Latest year"},0),B33,B34,B35) -> 510500
A38: Selected SDE margin (on latest revenue) | B38: =IF(D6=0,0,B37/D6) -> 0.28679775
A39: Revenue trend (Year 1 to Year 3, per year) | B39: =IF(B6<=0,0,(D6/B6)^(1/2)-1) -> 0.082151852

Sheet Valuation
A1: Valuation
A2: What the business is worth on a multiple of SDE, and the most its cash flow can support. | F2: Free demo · Get the full analyzer on Etsy →
A4: Multiples
A5: Selected SDE | B5: ='SDE Normalization'!$B$37 -> 510500
A6: Asking price | B6: ='Deal Inputs'!$B$10 -> 1850000
A7: Your offer | B7: ='Deal Inputs'!$B$11 -> 1750000
A8: Asking price ÷ SDE | B8: =IF(B5=0,0,B6/B5) -> 3.6238981
A9: Your offer ÷ SDE | B9: =IF(B5=0,0,B7/B5) -> 3.4280118
A10: Asking price ÷ latest revenue | B10: =IF('SDE Normalization'!$D$6=0,0,B6/'SDE Normalization'!$D$6) -> 1.0393258
A11: Your offer ÷ EBITDA (SDE − your salary) | B11: =IF((B5-'Deal Inputs'!$B$28)<=0,0,B7/(B5-'Deal Inputs'!$B$28)) -> 4.3695381
A13: Value range from SDE multiples
B14: Low | C14: Mid | D14: High
A15: SDE multiple (your research) | B15: 2.5 | C15: 3 | D15: 3.5 | F15: Example range only. Research recent sales in your industry and size (brokers, BizBuySell, comps).
A16: Implied value | B16: =$B$5*B15 -> 1276250 | C16: =$B$5*C15 -> 1531500 | D16: =$B$5*D15 -> 1786750
A17: Your offer vs implied value | B17: =IF(B16=0,0,$B$7/B16-1) -> 0.3712047 | C17: =IF(C16=0,0,$B$7/C16-1) -> 0.14267058 | D17: =IF(D16=0,0,$B$7/D16-1) -> -0.020568071
A18: Where your offer sits | B18: =IF(B7<B16,"✓ Below the low end of the range",IF(B7<=C16,"✓ Between low and mid",IF(B7<=D16,"! Between mid and high","✗ Above the high end of the range"))) -> ! Between mid and high
A20: Maximum price the cash flow can support
A21: Cash flow available for debt (SDE − your salary − capex) | B21: =B5-'Deal Inputs'!$B$28-'Deal Inputs'!$B$29 -> 370500 | F21: This is the money left to pay lenders after you pay yourself and keep equipment running.
A22: Target DSCR | B22: ='Deal Inputs'!$B$25 -> 1.25
A23: Maximum annual debt service at target DSCR | B23: =IF(B22=0,0,B21/B22) -> 296400
A24: Maximum loan that payment supports | B24: =PV('Deal Inputs'!$B$23/12,'Deal Inputs'!$B$24*12,-B23/12) -> 1830511
A25: MAXIMUM SUPPORTABLE PRICE | B25: =MAX(0,(B24/(1+'Deal Inputs'!$B$14)-('Deal Inputs'!$B$12+'Deal Inputs'!$B$13)*(1-'Deal Inputs'!$B$17))/(1-'Deal Inputs'!$B$17-'Deal Inputs'!$B$19)) -> 2092119 | F25: Assumes your cash injection % and seller note % from Deal Inputs, with seller
A26: Your offer vs maximum supportable price | B26: =IF(B25<=0,"✗ Cash flow cannot support this financing",IF(B7<=B25,"✓ Offer is within what the cash flow supports","✗ Offer is above what the cash flow supports")) -> ✓ Offer is within what the cash flow supports | F26: note payments on standby in the early years. Excludes taxes.
